agent_identity_python_sdk/__init__.py
agent_identity_python_sdk/context/__init__.py
agent_identity_python_sdk/context/context.py
agent_identity_python_sdk/core/__init__.py
agent_identity_python_sdk/core/decorators.py
agent_identity_python_sdk/core/identity.py
agent_identity_python_sdk/model/__init__.py
agent_identity_python_sdk/model/stscredential.py
agent_identity_python_sdk/utils/__init__.py
agent_identity_python_sdk/utils/cache.py
agent_identity_python_sdk/utils/config.py
agent_identity_python_sdk-0.1.1.dist-info/METADATA
agent_identity_python_sdk-0.1.1.dist-info/WHEEL
agent_identity_python_sdk-0.1.1.dist-info/top_level.txt
agent_identity_python_sdk-0.1.1.dist-info/RECORD
