Metadata-Version: 2.1
Name: agent-identity-python-sdk
Version: 0.1.1
Summary: Python SDK for using Agent Identity Service
Home-page: https://github.com/aliyun/agent-identity-dev-kit
Author: shaoheng
Author-email: liuyuhao.lyh@alibaba-inc.com
License: Apache-2.0
Classifier: Development Status :: 4 - Beta
Classifier: Intended Audience :: Developers
Classifier: License :: OSI Approved :: Apache Software License
Classifier: Operating System :: OS Independent
Classifier: Programming Language :: Python :: 3
Classifier: Programming Language :: Python :: 3.10
Classifier: Programming Language :: Python :: 3.11
Classifier: Programming Language :: Python :: 3.12
Classifier: Programming Language :: Python :: 3.13
Requires-Python: >=3.10
Requires-Dist: alibabacloud-agentidentity20250901 (>=1.0.1)
Requires-Dist: alibabacloud-agentidentitydata20251127 (>=1.0.2)
Requires-Dist: pydantic (==2.11.7)
Requires-Dist: setuptools
Requires-Dist: urllib3 (==2.3.0)
Requires-Dist: utils (==1.0.2)
Provides-Extra: dev
Requires-Dist: pytest-asyncio (>=0.24.0) ; extra == 'dev'
Requires-Dist: pytest-cov (>=6.0.0) ; extra == 'dev'
Requires-Dist: pytest (>=8.4.1) ; extra == 'dev'
